README.md
pyproject.toml
setup.cfg
setup.py
baseapp_organizations/__init__.py
baseapp_organizations.egg-info/PKG-INFO
baseapp_organizations.egg-info/SOURCES.txt
baseapp_organizations.egg-info/dependency_links.txt
baseapp_organizations.egg-info/top_level.txt